tuneta/__init__.py
tuneta/config.py
tuneta/optimize.py
tuneta/tune_ta.py
tuneta/utils.py
tuneta-0.1.43.dist-info/LICENSE
tuneta-0.1.43.dist-info/METADATA
tuneta-0.1.43.dist-info/WHEEL
tuneta-0.1.43.dist-info/top_level.txt
tuneta-0.1.43.dist-info/RECORD
