Metadata-Version: 2.1
Name: tuneta
Version: 0.1.43
Summary: Optimize financial technical indicators for machine learning
Home-page: https://github.com/jmrichardson/tuneta
Author: John Richardson
Author-email: jmrichardson@gmail.com
Keywords: technical analysis optimize tune indicators machine learning optuna tune hyperparameter optimization AI correlation
Classifier: Programming Language :: Python :: 3
Classifier: License :: OSI Approved :: MIT License
Classifier: Development Status :: 4 - Beta
Classifier: Natural Language :: English
Classifier: Operating System :: OS Independent
Requires-Python: >=3.6
License-File: LICENSE
Requires-Dist: pandas-ta
Requires-Dist: finta
Requires-Dist: ta-lib
Requires-Dist: pathos
Requires-Dist: tabulate
Requires-Dist: dcor (==0.5)
Requires-Dist: yfinance
Requires-Dist: optuna
Requires-Dist: yellowbrick
Requires-Dist: scikit-learn
Requires-Dist: pandas
Requires-Dist: numpy
Requires-Dist: numba
Requires-Dist: kmodes
